{
  "id": "53412daf-77ed-4e93-a4d3-6004910ecb49",
  "prevId": "8e7471d6-f540-4151-ad10-696a79515355",
  "version": "7",
  "dialect": "postgresql",
  "tables": {
    "public.financial_data": {
      "name": "financial_data",
      "schema": "",
      "columns": {
        "id": {
          "name": "id",
          "type": "uuid",
          "primaryKey": true,
          "notNull": true,
          "default": "gen_random_uuid()"
        },
        "stock_id": {
          "name": "stock_id",
          "type": "uuid",
          "primaryKey": false,
          "notNull": true
        },
        "period": {
          "name": "period",
          "type": "period",
          "typeSchema": "public",
          "primaryKey": false,
          "notNull": true
        },
        "year": {
          "name": "year",
          "type": "integer",
          "primaryKey": false,
          "notNull": true
        },
        "revenue": {
          "name": "revenue",
          "type": "numeric",
          "primaryKey": false,
          "notNull": false
        },
        "net_income": {
          "name": "net_income",
          "type": "numeric",
          "primaryKey": false,
          "notNull": false
        },
        "eps": {
          "name": "eps",
          "type": "numeric",
          "primaryKey": false,
          "notNull": false
        },
        "pe_ratio": {
          "name": "pe_ratio",
          "type": "numeric",
          "primaryKey": false,
          "notNull": false
        },
        "debt_to_equity": {
          "name": "debt_to_equity",
          "type": "numeric",
          "primaryKey": false,
          "notNull": false
        },
        "roe": {
          "name": "roe",
          "type": "numeric",
          "primaryKey": false,
          "notNull": false
        },
        "free_cash_flow": {
          "name": "free_cash_flow",
          "type": "numeric",
          "primaryKey": false,
          "notNull": false
        },
        "dividend_yield": {
          "name": "dividend_yield",
          "type": "numeric",
          "primaryKey": false,
          "notNull": false
        },
        "report_date": {
          "name": "report_date",
          "type": "timestamp",
          "primaryKey": false,
          "notNull": false
        }
      },
      "indexes": {
        "financial_stock_idx": {
          "name": "financial_stock_idx",
          "columns": [
            {
              "expression": "stock_id",
              "isExpression": false,
              "asc": true,
              "nulls": "last"
            }
          ],
          "isUnique": false,
          "concurrently": false,
          "method": "btree",
          "with": {}
        },
        "financial_stock_period_year": {
          "name": "financial_stock_period_year",
          "columns": [
            {
              "expression": "stock_id",
              "isExpression": false,
              "asc": true,
              "nulls": "last"
            },
            {
              "expression": "period",
              "isExpression": false,
              "asc": true,
              "nulls": "last"
            },
            {
              "expression": "year",
              "isExpression": false,
              "asc": true,
              "nulls": "last"
            }
          ],
          "isUnique": true,
          "concurrently": false,
          "method": "btree",
          "with": {}
        }
      },
      "foreignKeys": {
        "financial_data_stock_id_stocks_id_fk": {
          "name": "financial_data_stock_id_stocks_id_fk",
          "tableFrom": "financial_data",
          "tableTo": "stocks",
          "columnsFrom": [
            "stock_id"
          ],
          "columnsTo": [
            "id"
          ],
          "onDelete": "cascade",
          "onUpdate": "no action"
        }
      },
      "compositePrimaryKeys": {},
      "uniqueConstraints": {},
      "policies": {},
      "checkConstraints": {},
      "isRLSEnabled": false
    },
    "public.market_equities": {
      "name": "market_equities",
      "schema": "",
      "columns": {
        "id": {
          "name": "id",
          "type": "uuid",
          "primaryKey": true,
          "notNull": true,
          "default": "gen_random_uuid()"
        },
        "symbol": {
          "name": "symbol",
          "type": "varchar(32)",
          "primaryKey": false,
          "notNull": true
        },
        "name": {
          "name": "name",
          "type": "varchar(255)",
          "primaryKey": false,
          "notNull": true
        },
        "exchange": {
          "name": "exchange",
          "type": "varchar(64)",
          "primaryKey": false,
          "notNull": true
        },
        "country": {
          "name": "country",
          "type": "varchar(2)",
          "primaryKey": false,
          "notNull": true
        },
        "region": {
          "name": "region",
          "type": "varchar(8)",
          "primaryKey": false,
          "notNull": true
        },
        "currency": {
          "name": "currency",
          "type": "varchar(8)",
          "primaryKey": false,
          "notNull": true,
          "default": "'USD'"
        },
        "sector": {
          "name": "sector",
          "type": "varchar(100)",
          "primaryKey": false,
          "notNull": false
        },
        "industry": {
          "name": "industry",
          "type": "varchar(100)",
          "primaryKey": false,
          "notNull": false
        },
        "price": {
          "name": "price",
          "type": "numeric",
          "primaryKey": false,
          "notNull": true
        },
        "change_pct": {
          "name": "change_pct",
          "type": "numeric",
          "primaryKey": false,
          "notNull": false
        },
        "volume": {
          "name": "volume",
          "type": "numeric",
          "primaryKey": false,
          "notNull": false
        },
        "market_cap": {
          "name": "market_cap",
          "type": "numeric",
          "primaryKey": false,
          "notNull": false
        },
        "pe_ratio": {
          "name": "pe_ratio",
          "type": "numeric",
          "primaryKey": false,
          "notNull": false
        },
        "roe": {
          "name": "roe",
          "type": "numeric",
          "primaryKey": false,
          "notNull": false
        },
        "dividend_yield": {
          "name": "dividend_yield",
          "type": "numeric",
          "primaryKey": false,
          "notNull": false
        },
        "composite_score": {
          "name": "composite_score",
          "type": "numeric",
          "primaryKey": false,
          "notNull": false
        },
        "updated_at": {
          "name": "updated_at",
          "type": "timestamp",
          "primaryKey": false,
          "notNull": true,
          "default": "now()"
        }
      },
      "indexes": {
        "market_equities_symbol_exchange_idx": {
          "name": "market_equities_symbol_exchange_idx",
          "columns": [
            {
              "expression": "symbol",
              "isExpression": false,
              "asc": true,
              "nulls": "last"
            },
            {
              "expression": "exchange",
              "isExpression": false,
              "asc": true,
              "nulls": "last"
            }
          ],
          "isUnique": true,
          "concurrently": false,
          "method": "btree",
          "with": {}
        },
        "market_equities_region_idx": {
          "name": "market_equities_region_idx",
          "columns": [
            {
              "expression": "region",
              "isExpression": false,
              "asc": true,
              "nulls": "last"
            }
          ],
          "isUnique": false,
          "concurrently": false,
          "method": "btree",
          "with": {}
        },
        "market_equities_sector_idx": {
          "name": "market_equities_sector_idx",
          "columns": [
            {
              "expression": "sector",
              "isExpression": false,
              "asc": true,
              "nulls": "last"
            }
          ],
          "isUnique": false,
          "concurrently": false,
          "method": "btree",
          "with": {}
        },
        "market_equities_market_cap_idx": {
          "name": "market_equities_market_cap_idx",
          "columns": [
            {
              "expression": "market_cap",
              "isExpression": false,
              "asc": true,
              "nulls": "last"
            }
          ],
          "isUnique": false,
          "concurrently": false,
          "method": "btree",
          "with": {}
        }
      },
      "foreignKeys": {},
      "compositePrimaryKeys": {},
      "uniqueConstraints": {},
      "policies": {},
      "checkConstraints": {},
      "isRLSEnabled": false
    },
    "public.news_articles": {
      "name": "news_articles",
      "schema": "",
      "columns": {
        "id": {
          "name": "id",
          "type": "uuid",
          "primaryKey": true,
          "notNull": true,
          "default": "gen_random_uuid()"
        },
        "stock_id": {
          "name": "stock_id",
          "type": "uuid",
          "primaryKey": false,
          "notNull": false
        },
        "title": {
          "name": "title",
          "type": "text",
          "primaryKey": false,
          "notNull": true
        },
        "summary": {
          "name": "summary",
          "type": "text",
          "primaryKey": false,
          "notNull": false
        },
        "source_url": {
          "name": "source_url",
          "type": "text",
          "primaryKey": false,
          "notNull": true
        },
        "source_name": {
          "name": "source_name",
          "type": "varchar(100)",
          "primaryKey": false,
          "notNull": false
        },
        "sentiment": {
          "name": "sentiment",
          "type": "sentiment",
          "typeSchema": "public",
          "primaryKey": false,
          "notNull": false
        },
        "image_url": {
          "name": "image_url",
          "type": "text",
          "primaryKey": false,
          "notNull": false
        },
        "published_at": {
          "name": "published_at",
          "type": "timestamp",
          "primaryKey": false,
          "notNull": true
        },
        "created_at": {
          "name": "created_at",
          "type": "timestamp",
          "primaryKey": false,
          "notNull": true,
          "default": "now()"
        }
      },
      "indexes": {
        "news_stock_idx": {
          "name": "news_stock_idx",
          "columns": [
            {
              "expression": "stock_id",
              "isExpression": false,
              "asc": true,
              "nulls": "last"
            }
          ],
          "isUnique": false,
          "concurrently": false,
          "method": "btree",
          "with": {}
        },
        "news_published_idx": {
          "name": "news_published_idx",
          "columns": [
            {
              "expression": "published_at",
              "isExpression": false,
              "asc": true,
              "nulls": "last"
            }
          ],
          "isUnique": false,
          "concurrently": false,
          "method": "btree",
          "with": {}
        }
      },
      "foreignKeys": {
        "news_articles_stock_id_stocks_id_fk": {
          "name": "news_articles_stock_id_stocks_id_fk",
          "tableFrom": "news_articles",
          "tableTo": "stocks",
          "columnsFrom": [
            "stock_id"
          ],
          "columnsTo": [
            "id"
          ],
          "onDelete": "set null",
          "onUpdate": "no action"
        }
      },
      "compositePrimaryKeys": {},
      "uniqueConstraints": {},
      "policies": {},
      "checkConstraints": {},
      "isRLSEnabled": false
    },
    "public.portfolio_holdings": {
      "name": "portfolio_holdings",
      "schema": "",
      "columns": {
        "id": {
          "name": "id",
          "type": "uuid",
          "primaryKey": true,
          "notNull": true,
          "default": "gen_random_uuid()"
        },
        "portfolio_id": {
          "name": "portfolio_id",
          "type": "uuid",
          "primaryKey": false,
          "notNull": true
        },
        "stock_id": {
          "name": "stock_id",
          "type": "uuid",
          "primaryKey": false,
          "notNull": true
        },
        "shares": {
          "name": "shares",
          "type": "numeric",
          "primaryKey": false,
          "notNull": true
        },
        "avg_cost_basis": {
          "name": "avg_cost_basis",
          "type": "numeric",
          "primaryKey": false,
          "notNull": true
        },
        "purchase_date": {
          "name": "purchase_date",
          "type": "timestamp",
          "primaryKey": false,
          "notNull": false
        }
      },
      "indexes": {},
      "foreignKeys": {
        "portfolio_holdings_portfolio_id_portfolios_id_fk": {
          "name": "portfolio_holdings_portfolio_id_portfolios_id_fk",
          "tableFrom": "portfolio_holdings",
          "tableTo": "portfolios",
          "columnsFrom": [
            "portfolio_id"
          ],
          "columnsTo": [
            "id"
          ],
          "onDelete": "cascade",
          "onUpdate": "no action"
        },
        "portfolio_holdings_stock_id_stocks_id_fk": {
          "name": "portfolio_holdings_stock_id_stocks_id_fk",
          "tableFrom": "portfolio_holdings",
          "tableTo": "stocks",
          "columnsFrom": [
            "stock_id"
          ],
          "columnsTo": [
            "id"
          ],
          "onDelete": "cascade",
          "onUpdate": "no action"
        }
      },
      "compositePrimaryKeys": {},
      "uniqueConstraints": {},
      "policies": {},
      "checkConstraints": {},
      "isRLSEnabled": false
    },
    "public.portfolios": {
      "name": "portfolios",
      "schema": "",
      "columns": {
        "id": {
          "name": "id",
          "type": "uuid",
          "primaryKey": true,
          "notNull": true,
          "default": "gen_random_uuid()"
        },
        "user_id": {
          "name": "user_id",
          "type": "uuid",
          "primaryKey": false,
          "notNull": true
        },
        "name": {
          "name": "name",
          "type": "varchar(100)",
          "primaryKey": false,
          "notNull": true
        },
        "created_at": {
          "name": "created_at",
          "type": "timestamp",
          "primaryKey": false,
          "notNull": true,
          "default": "now()"
        }
      },
      "indexes": {},
      "foreignKeys": {
        "portfolios_user_id_users_id_fk": {
          "name": "portfolios_user_id_users_id_fk",
          "tableFrom": "portfolios",
          "tableTo": "users",
          "columnsFrom": [
            "user_id"
          ],
          "columnsTo": [
            "id"
          ],
          "onDelete": "cascade",
          "onUpdate": "no action"
        }
      },
      "compositePrimaryKeys": {},
      "uniqueConstraints": {},
      "policies": {},
      "checkConstraints": {},
      "isRLSEnabled": false
    },
    "public.stock_analyses": {
      "name": "stock_analyses",
      "schema": "",
      "columns": {
        "id": {
          "name": "id",
          "type": "uuid",
          "primaryKey": true,
          "notNull": true,
          "default": "gen_random_uuid()"
        },
        "stock_id": {
          "name": "stock_id",
          "type": "uuid",
          "primaryKey": false,
          "notNull": true
        },
        "overall_score": {
          "name": "overall_score",
          "type": "numeric",
          "primaryKey": false,
          "notNull": true
        },
        "value_score": {
          "name": "value_score",
          "type": "numeric",
          "primaryKey": false,
          "notNull": true
        },
        "growth_score": {
          "name": "growth_score",
          "type": "numeric",
          "primaryKey": false,
          "notNull": true
        },
        "profitability_score": {
          "name": "profitability_score",
          "type": "numeric",
          "primaryKey": false,
          "notNull": true
        },
        "dividend_score": {
          "name": "dividend_score",
          "type": "numeric",
          "primaryKey": false,
          "notNull": true
        },
        "health_score": {
          "name": "health_score",
          "type": "numeric",
          "primaryKey": false,
          "notNull": true
        },
        "ai_summary": {
          "name": "ai_summary",
          "type": "text",
          "primaryKey": false,
          "notNull": false
        },
        "ai_sentiment": {
          "name": "ai_sentiment",
          "type": "sentiment",
          "typeSchema": "public",
          "primaryKey": false,
          "notNull": false
        },
        "strengths": {
          "name": "strengths",
          "type": "text[]",
          "primaryKey": false,
          "notNull": false
        },
        "weaknesses": {
          "name": "weaknesses",
          "type": "text[]",
          "primaryKey": false,
          "notNull": false
        },
        "generated_at": {
          "name": "generated_at",
          "type": "timestamp",
          "primaryKey": false,
          "notNull": true,
          "default": "now()"
        }
      },
      "indexes": {
        "analyses_stock_idx": {
          "name": "analyses_stock_idx",
          "columns": [
            {
              "expression": "stock_id",
              "isExpression": false,
              "asc": true,
              "nulls": "last"
            }
          ],
          "isUnique": false,
          "concurrently": false,
          "method": "btree",
          "with": {}
        }
      },
      "foreignKeys": {
        "stock_analyses_stock_id_stocks_id_fk": {
          "name": "stock_analyses_stock_id_stocks_id_fk",
          "tableFrom": "stock_analyses",
          "tableTo": "stocks",
          "columnsFrom": [
            "stock_id"
          ],
          "columnsTo": [
            "id"
          ],
          "onDelete": "cascade",
          "onUpdate": "no action"
        }
      },
      "compositePrimaryKeys": {},
      "uniqueConstraints": {},
      "policies": {},
      "checkConstraints": {},
      "isRLSEnabled": false
    },
    "public.stocks": {
      "name": "stocks",
      "schema": "",
      "columns": {
        "id": {
          "name": "id",
          "type": "uuid",
          "primaryKey": true,
          "notNull": true,
          "default": "gen_random_uuid()"
        },
        "ticker": {
          "name": "ticker",
          "type": "varchar(10)",
          "primaryKey": false,
          "notNull": true
        },
        "name": {
          "name": "name",
          "type": "varchar(255)",
          "primaryKey": false,
          "notNull": true
        },
        "exchange": {
          "name": "exchange",
          "type": "varchar(20)",
          "primaryKey": false,
          "notNull": true
        },
        "sector": {
          "name": "sector",
          "type": "varchar(100)",
          "primaryKey": false,
          "notNull": false
        },
        "industry": {
          "name": "industry",
          "type": "varchar(100)",
          "primaryKey": false,
          "notNull": false
        },
        "market_cap": {
          "name": "market_cap",
          "type": "numeric",
          "primaryKey": false,
          "notNull": false
        },
        "currency": {
          "name": "currency",
          "type": "varchar(10)",
          "primaryKey": false,
          "notNull": true,
          "default": "'USD'"
        },
        "logo_url": {
          "name": "logo_url",
          "type": "text",
          "primaryKey": false,
          "notNull": false
        },
        "last_updated": {
          "name": "last_updated",
          "type": "timestamp",
          "primaryKey": false,
          "notNull": true,
          "default": "now()"
        }
      },
      "indexes": {
        "stocks_ticker_idx": {
          "name": "stocks_ticker_idx",
          "columns": [
            {
              "expression": "ticker",
              "isExpression": false,
              "asc": true,
              "nulls": "last"
            }
          ],
          "isUnique": true,
          "concurrently": false,
          "method": "btree",
          "with": {}
        },
        "stocks_sector_idx": {
          "name": "stocks_sector_idx",
          "columns": [
            {
              "expression": "sector",
              "isExpression": false,
              "asc": true,
              "nulls": "last"
            }
          ],
          "isUnique": false,
          "concurrently": false,
          "method": "btree",
          "with": {}
        }
      },
      "foreignKeys": {},
      "compositePrimaryKeys": {},
      "uniqueConstraints": {},
      "policies": {},
      "checkConstraints": {},
      "isRLSEnabled": false
    },
    "public.user_preferences": {
      "name": "user_preferences",
      "schema": "",
      "columns": {
        "id": {
          "name": "id",
          "type": "uuid",
          "primaryKey": true,
          "notNull": true,
          "default": "gen_random_uuid()"
        },
        "user_id": {
          "name": "user_id",
          "type": "uuid",
          "primaryKey": false,
          "notNull": true
        },
        "theme": {
          "name": "theme",
          "type": "varchar(10)",
          "primaryKey": false,
          "notNull": true,
          "default": "'system'"
        },
        "default_screener_filters": {
          "name": "default_screener_filters",
          "type": "text",
          "primaryKey": false,
          "notNull": false
        },
        "notifications_enabled": {
          "name": "notifications_enabled",
          "type": "boolean",
          "primaryKey": false,
          "notNull": true,
          "default": true
        }
      },
      "indexes": {},
      "foreignKeys": {
        "user_preferences_user_id_users_id_fk": {
          "name": "user_preferences_user_id_users_id_fk",
          "tableFrom": "user_preferences",
          "tableTo": "users",
          "columnsFrom": [
            "user_id"
          ],
          "columnsTo": [
            "id"
          ],
          "onDelete": "cascade",
          "onUpdate": "no action"
        }
      },
      "compositePrimaryKeys": {},
      "uniqueConstraints": {
        "user_preferences_user_id_unique": {
          "name": "user_preferences_user_id_unique",
          "nullsNotDistinct": false,
          "columns": [
            "user_id"
          ]
        }
      },
      "policies": {},
      "checkConstraints": {},
      "isRLSEnabled": false
    },
    "public.users": {
      "name": "users",
      "schema": "",
      "columns": {
        "id": {
          "name": "id",
          "type": "uuid",
          "primaryKey": true,
          "notNull": true,
          "default": "gen_random_uuid()"
        },
        "email": {
          "name": "email",
          "type": "varchar(255)",
          "primaryKey": false,
          "notNull": true
        },
        "name": {
          "name": "name",
          "type": "varchar(255)",
          "primaryKey": false,
          "notNull": false
        },
        "avatar_url": {
          "name": "avatar_url",
          "type": "text",
          "primaryKey": false,
          "notNull": false
        },
        "plan": {
          "name": "plan",
          "type": "plan",
          "typeSchema": "public",
          "primaryKey": false,
          "notNull": true,
          "default": "'free'"
        },
        "created_at": {
          "name": "created_at",
          "type": "timestamp",
          "primaryKey": false,
          "notNull": true,
          "default": "now()"
        },
        "updated_at": {
          "name": "updated_at",
          "type": "timestamp",
          "primaryKey": false,
          "notNull": true,
          "default": "now()"
        }
      },
      "indexes": {},
      "foreignKeys": {},
      "compositePrimaryKeys": {},
      "uniqueConstraints": {
        "users_email_unique": {
          "name": "users_email_unique",
          "nullsNotDistinct": false,
          "columns": [
            "email"
          ]
        }
      },
      "policies": {},
      "checkConstraints": {},
      "isRLSEnabled": false
    },
    "public.watchlist_stocks": {
      "name": "watchlist_stocks",
      "schema": "",
      "columns": {
        "id": {
          "name": "id",
          "type": "uuid",
          "primaryKey": true,
          "notNull": true,
          "default": "gen_random_uuid()"
        },
        "watchlist_id": {
          "name": "watchlist_id",
          "type": "uuid",
          "primaryKey": false,
          "notNull": true
        },
        "stock_id": {
          "name": "stock_id",
          "type": "uuid",
          "primaryKey": false,
          "notNull": true
        },
        "notes": {
          "name": "notes",
          "type": "text",
          "primaryKey": false,
          "notNull": false
        },
        "added_at": {
          "name": "added_at",
          "type": "timestamp",
          "primaryKey": false,
          "notNull": true,
          "default": "now()"
        }
      },
      "indexes": {
        "watchlist_stock_unique": {
          "name": "watchlist_stock_unique",
          "columns": [
            {
              "expression": "watchlist_id",
              "isExpression": false,
              "asc": true,
              "nulls": "last"
            },
            {
              "expression": "stock_id",
              "isExpression": false,
              "asc": true,
              "nulls": "last"
            }
          ],
          "isUnique": true,
          "concurrently": false,
          "method": "btree",
          "with": {}
        }
      },
      "foreignKeys": {
        "watchlist_stocks_watchlist_id_watchlists_id_fk": {
          "name": "watchlist_stocks_watchlist_id_watchlists_id_fk",
          "tableFrom": "watchlist_stocks",
          "tableTo": "watchlists",
          "columnsFrom": [
            "watchlist_id"
          ],
          "columnsTo": [
            "id"
          ],
          "onDelete": "cascade",
          "onUpdate": "no action"
        },
        "watchlist_stocks_stock_id_stocks_id_fk": {
          "name": "watchlist_stocks_stock_id_stocks_id_fk",
          "tableFrom": "watchlist_stocks",
          "tableTo": "stocks",
          "columnsFrom": [
            "stock_id"
          ],
          "columnsTo": [
            "id"
          ],
          "onDelete": "cascade",
          "onUpdate": "no action"
        }
      },
      "compositePrimaryKeys": {},
      "uniqueConstraints": {},
      "policies": {},
      "checkConstraints": {},
      "isRLSEnabled": false
    },
    "public.watchlists": {
      "name": "watchlists",
      "schema": "",
      "columns": {
        "id": {
          "name": "id",
          "type": "uuid",
          "primaryKey": true,
          "notNull": true,
          "default": "gen_random_uuid()"
        },
        "user_id": {
          "name": "user_id",
          "type": "uuid",
          "primaryKey": false,
          "notNull": true
        },
        "name": {
          "name": "name",
          "type": "varchar(100)",
          "primaryKey": false,
          "notNull": true
        },
        "is_default": {
          "name": "is_default",
          "type": "boolean",
          "primaryKey": false,
          "notNull": true,
          "default": false
        },
        "created_at": {
          "name": "created_at",
          "type": "timestamp",
          "primaryKey": false,
          "notNull": true,
          "default": "now()"
        }
      },
      "indexes": {},
      "foreignKeys": {
        "watchlists_user_id_users_id_fk": {
          "name": "watchlists_user_id_users_id_fk",
          "tableFrom": "watchlists",
          "tableTo": "users",
          "columnsFrom": [
            "user_id"
          ],
          "columnsTo": [
            "id"
          ],
          "onDelete": "cascade",
          "onUpdate": "no action"
        }
      },
      "compositePrimaryKeys": {},
      "uniqueConstraints": {},
      "policies": {},
      "checkConstraints": {},
      "isRLSEnabled": false
    }
  },
  "enums": {
    "public.period": {
      "name": "period",
      "schema": "public",
      "values": [
        "Q1",
        "Q2",
        "Q3",
        "Q4",
        "FY"
      ]
    },
    "public.plan": {
      "name": "plan",
      "schema": "public",
      "values": [
        "free",
        "pro",
        "premium"
      ]
    },
    "public.sentiment": {
      "name": "sentiment",
      "schema": "public",
      "values": [
        "bullish",
        "somewhat_bullish",
        "neutral",
        "somewhat_bearish",
        "bearish"
      ]
    }
  },
  "schemas": {},
  "sequences": {},
  "roles": {},
  "policies": {},
  "views": {},
  "_meta": {
    "columns": {},
    "schemas": {},
    "tables": {}
  }
}